videoreader.py
pyvideoreader-0.5.7.dist-info/LICENSE
pyvideoreader-0.5.7.dist-info/WHEEL
pyvideoreader-0.5.7.dist-info/METADATA
pyvideoreader-0.5.7.dist-info/RECORD
