Metadata-Version: 2.1
Name: pyvideoreader
Version: 0.5.7
Summary: Wrapper around opencv's cv2.VideoCapture to simplify reading video files in python.
Author-email: Jan Clemens <clemensjan@googlemail.com>
Requires-Python: >=3.9
Classifier: License :: OSI Approved :: MIT License
Requires-Dist: opencv-python-headless>=3.0
Project-URL: Documentation, https://github.com/postpop/videoreader
Project-URL: Source, https://github.com/postpop/videoreader
